cg_feedback_helpers/__init__.py
cg_feedback_helpers/_impl/__init__.py
cg_feedback_helpers/_impl/assertions.py
cg_feedback_helpers/_impl/compatibility_layer.py
cg_feedback_helpers/_impl/config.py
cg_feedback_helpers/_impl/makers.py
cg_feedback_helpers/_impl/types.py
cg_feedback_helpers/_impl/writers.py
cg_feedback_helpers/helpers.py
cg_feedback_helpers-2024.2.26.1339.dist-info/METADATA
cg_feedback_helpers-2024.2.26.1339.dist-info/WHEEL
cg_feedback_helpers-2024.2.26.1339.dist-info/RECORD
