Metadata-Version: 2.1
Name: cg-feedback-helpers
Version: 2024.2.26.1339
Summary: 
License: MIT
Author: CodeGrade
Author-email: info@codegrade.com
Requires-Python: >=3.10,<4.0
Classifier: License :: OSI Approved :: MIT License
Classifier: Programming Language :: Python :: 3
Classifier: Programming Language :: Python :: 3.10
Classifier: Programming Language :: Python :: 3.11
Classifier: Programming Language :: Python :: 3.12
